odoo/addons/edi_product_multi_barcode_oca/README.rst
odoo/addons/edi_product_multi_barcode_oca/__init__.py
odoo/addons/edi_product_multi_barcode_oca/__manifest__.py
odoo/addons/edi_product_multi_barcode_oca/i18n/edi_product_multi_barcode_oca.pot
odoo/addons/edi_product_multi_barcode_oca/i18n/it.po
odoo/addons/edi_product_multi_barcode_oca/models/__init__.py
odoo/addons/edi_product_multi_barcode_oca/models/product_barcode.py
odoo/addons/edi_product_multi_barcode_oca/readme/CONTRIBUTORS.rst
odoo/addons/edi_product_multi_barcode_oca/readme/CREDITS.rst
odoo/addons/edi_product_multi_barcode_oca/readme/DESCRIPTION.rst
odoo/addons/edi_product_multi_barcode_oca/static/description/icon.png
odoo/addons/edi_product_multi_barcode_oca/static/description/index.html
odoo_addon_edi_product_multi_barcode_oca-16.0.1.0.0.12.dist-info/METADATA
odoo_addon_edi_product_multi_barcode_oca-16.0.1.0.0.12.dist-info/WHEEL
odoo_addon_edi_product_multi_barcode_oca-16.0.1.0.0.12.dist-info/top_level.txt
odoo_addon_edi_product_multi_barcode_oca-16.0.1.0.0.12.dist-info/RECORD
